laminlake/__init__.py
laminlake/__main__.py
laminlake/_notion.py
laminlake/_s3.py
laminlake-0.2.0.dist-info/entry_points.txt
laminlake-0.2.0.dist-info/WHEEL
laminlake-0.2.0.dist-info/METADATA
laminlake-0.2.0.dist-info/RECORD
