Metadata-Version: 2.1
Name: laminlake
Version: 0.2.0
Summary: Lamin Lake.
Author-email: Lamin Dev <laminlabs@gmail.com>
Requires-Dist: boto3
Requires-Dist: anndata
Requires-Dist: pre-commit ; extra == "dev"
Requires-Dist: black ; extra == "dev"
Requires-Dist: pytest>=6.0 ; extra == "test"
Requires-Dist: nbmake ; extra == "test"
Project-URL: Home, https://github.com/laminlabs/laminlake
Provides-Extra: dev
Provides-Extra: doc
Provides-Extra: test
